setup.py
crazy/__init__.py
crazy/dbx.py
crazy/factory.py
crazy/mysqlx.py
crazy/redisx.py
crazy/sql_util.py
crazy/table_dao.py
crazy/table_update_listener.py
crazy.egg-info/PKG-INFO
crazy.egg-info/SOURCES.txt
crazy.egg-info/dependency_links.txt
crazy.egg-info/not-zip-safe
crazy.egg-info/requires.txt
crazy.egg-info/top_level.txt